odoo8_addon_analytic_multicurrency-8.0.1.0.1-py2.7-nspkg.pth
odoo8_addon_analytic_multicurrency-8.0.1.0.1.dist-info/DESCRIPTION.rst
odoo8_addon_analytic_multicurrency-8.0.1.0.1.dist-info/METADATA
odoo8_addon_analytic_multicurrency-8.0.1.0.1.dist-info/RECORD
odoo8_addon_analytic_multicurrency-8.0.1.0.1.dist-info/WHEEL
odoo8_addon_analytic_multicurrency-8.0.1.0.1.dist-info/metadata.json
odoo8_addon_analytic_multicurrency-8.0.1.0.1.dist-info/namespace_packages.txt
odoo8_addon_analytic_multicurrency-8.0.1.0.1.dist-info/top_level.txt
odoo_addons/analytic_multicurrency/README.rst
odoo_addons/analytic_multicurrency/__init__.py
odoo_addons/analytic_multicurrency/__openerp__.py
odoo_addons/analytic_multicurrency/account_analytic_line.py
odoo_addons/analytic_multicurrency/analytic.py
odoo_addons/analytic_multicurrency/analytic_analysis.py
odoo_addons/analytic_multicurrency/analytic_view.xml
odoo_addons/analytic_multicurrency/i18n/ca.po
odoo_addons/analytic_multicurrency/i18n/de.po
odoo_addons/analytic_multicurrency/i18n/el_GR.po
odoo_addons/analytic_multicurrency/i18n/es.po
odoo_addons/analytic_multicurrency/i18n/es_MX.po
odoo_addons/analytic_multicurrency/i18n/fi.po
odoo_addons/analytic_multicurrency/i18n/fr.po
odoo_addons/analytic_multicurrency/i18n/pt.po
odoo_addons/analytic_multicurrency/i18n/pt_BR.po
odoo_addons/analytic_multicurrency/i18n/sk_SK.po
odoo_addons/analytic_multicurrency/i18n/sl.po
odoo_addons/analytic_multicurrency/i18n/zh_CN.po
odoo_addons/analytic_multicurrency/tests/__init__.py
odoo_addons/analytic_multicurrency/tests/test_analytic_lines.py
