Metadata-Version: 2.0
Name: odoo8-addon-analytic-multicurrency
Version: 8.0.1.0.1
Summary: Multi-Currency in Analytic Accounting
Home-page: http://camptocamp.com
Author: Camptocamp,Odoo Community Association (OCA)
Author-email: support@odoo-community.org
License: AGPL-3
Platform: UNKNOWN
Classifier: Programming Language :: Python
Classifier: Framework :: Odoo
Classifier: License :: OSI Approved :: GNU Affero General Public License v3
Requires-Python: ~=2.7
Requires-Dist: odoo (<9.0a,>=8.0a)
